{
  "notes": [
    {
      "id": 1,
      "content": "HTML is esay (db.json)",
      "date": "2019-05-30T17:30:31.098Z",
      "important": true
    },
    {
      "id": 2,
      "content": "Browser can execute only JavaScript (db.json)",
      "date": "2019-05-30T18:39:34.091Z",
      "important": false
    },
    {
      "id": 3,
      "content": "GET and POST are the most important methods of HTTP protocol (db.json)",
      "date": "2019-05-30T19:20:14.298Z",
      "important": false
    },
    {
      "content": "new note",
      "date": "2021-02-02T15:42:25.985Z",
      "important": true,
      "id": 4
    },
    {
      "content": "new note2",
      "date": "2021-02-02T18:02:38.661Z",
      "important": true,
      "id": 5
    }
  ]
}